email_notify_magic/__init__.py
email_notify_magic/email_notify_magic.py
email_notify_magic-0.0.2.dist-info/METADATA
email_notify_magic-0.0.2.dist-info/RECORD
email_notify_magic-0.0.2.dist-info/WHEEL
email_notify_magic-0.0.2.dist-info/top_level.txt
