Metadata-Version: 2.1
Name: email-notify-magic
Version: 0.0.2
Summary: A Jupyter magic for sending e-mail after cell completion
Home-page: https://github.com/caiofcm/email-notify-magic
Author: Caio Marcellos
Author-email: caiocuritiba@gmail.com
License: MIT
Platform: UNKNOWN
Classifier: License :: OSI Approved :: MIT License
Classifier: Programming Language :: Python :: 3
Classifier: Programming Language :: Python :: 3.7
Requires-Dist: ipython
